chevron-stubs/METADATA.toml
chevron-stubs/__init__.pyi
chevron-stubs/main.pyi
chevron-stubs/metadata.pyi
chevron-stubs/renderer.pyi
chevron-stubs/tokenizer.pyi
types_chevron-0.14.2.20240106.dist-info/METADATA
types_chevron-0.14.2.20240106.dist-info/WHEEL
types_chevron-0.14.2.20240106.dist-info/top_level.txt
types_chevron-0.14.2.20240106.dist-info/RECORD
